{"_id":"domelementtype","_rev":"41837630","name":"domelementtype","description":"all the types of nodes in htmlparser2's dom","dist-tags":{"latest":"2.0.1"},"maintainers":[{"name":"feedic","email":"me@feedic.com"}],"time":{"modified":"2019-07-30T19:23:45.000Z","created":"2012-11-10T13:34:56.751Z","2.0.1":"2019-07-30T19:23:33.163Z","2.0.0":"2019-07-30T18:32:04.234Z","1.3.1":"2018-12-06T09:27:33.391Z","1.2.1":"2018-10-21T23:40:43.885Z","1.3.0":"2015-03-03T09:59:23.974Z","1.2.0":"2015-03-03T09:57:11.527Z","1.1.3":"2014-10-30T11:04:12.175Z","1.1.2":"2014-10-30T11:01:56.102Z","1.1.1":"2013-02-15T07:43:13.702Z","1.1.0":"2013-01-09T14:48:09.118Z","1.0.1":"2012-12-04T14:15:50.441Z","1.0.0":"2012-11-10T13:34:56.751Z"},"users":{"mojaray2k":true,"shuoshubao":true,"soenkekluth":true},"author":{"name":"Felix Boehm","email":"me@feedic.com"},"repository":{"type":"git","url":"git://github.com/fb55/domelementtype.git"},"versions":{"2.0.1":{"name":"domelementtype","version":"2.0.1","description":"all the types of nodes in htmlparser2's dom","main":"lib/index.js","types":"lib/index.d.ts","repository":{"type":"git","url":"git://github.com/fb55/domelementtype.git"},"keywords":["dom","htmlparser2"],"scripts":{"test":"npm run lint && prettier --check **/*.{ts,json,md}","lint":"eslint **/*.ts","format":"prettier --write **/*.{ts,json,md}","build":"tsc","prepare":"npm run build"},"author":{"name":"Felix Boehm","email":"me@feedic.com"},"license":"BSD-2-Clause","prettier":{"tabWidth":4},"devDependencies":{"@typescript-eslint/eslint-plugin":"^1.13.0","@typescript-eslint/parser":"^1.13.0","eslint":"^6.1.0","eslint-config-prettier":"^6.0.0","prettier":"^1.18.2","typescript":"^3.5.3"},"gitHead":"e5d7d8a55fa6143334a7de90787abe01a178a351","bugs":{"url":"https://github.com/fb55/domelementtype/issues"},"homepage":"https://github.com/fb55/domelementtype#readme","_id":"domelementtype@2.0.1","_nodeVersion":"12.4.0","_npmVersion":"6.10.1","dist":{"shasum":"1f8bdfe91f5a78063274e803b4bdcedf6e94f94d","size":2199,"noattachment":false,"tarball":"https://registry.npm.taobao.org/domelementtype/download/domelementtype-2.0.1.tgz"},"maintainers":[{"name":"feedic","email":"me@feedic.com"}],"_npmUser":{"name":"feedic","email":"me@feedic.com"},"directories":{},"_npmOperationalInternal":{"host":"s3://npm-registry-packages","tmp":"tmp/domelementtype_2.0.1_1564514613068_0.8904122755116697"},"_hasShrinkwrap":false,"publish_time":1564514613163,"_cnpm_publish_time":1564514613163},"2.0.0":{"name":"domelementtype","version":"2.0.0","description":"all the types of nodes in htmlparser2's dom","main":"index.js","repository":{"type":"git","url":"git://github.com/fb55/domelementtype.git"},"keywords":["dom","htmlparser2"],"scripts":{"test":"npm run lint && prettier --check **/*.{ts,json,md}","lint":"eslint **/*.ts","format":"prettier --write **/*.{ts,json,md}","build":"tsc","prepare":"npm run build"},"author":{"name":"Felix Boehm","email":"me@feedic.com"},"license":"BSD-2-Clause","prettier":{"tabWidth":4},"devDependencies":{"@typescript-eslint/eslint-plugin":"^1.13.0","@typescript-eslint/parser":"^1.13.0","eslint":"^6.1.0","eslint-config-prettier":"^6.0.0","prettier":"^1.18.2","typescript":"^3.5.3"},"gitHead":"14fa78d35f2708fac49b9268bf2925ee1597dda7","bugs":{"url":"https://github.com/fb55/domelementtype/issues"},"homepage":"https://github.com/fb55/domelementtype#readme","_id":"domelementtype@2.0.0","_nodeVersion":"12.4.0","_npmVersion":"6.10.1","dist":{"shasum":"4a4d74a2a478923cb3a6db6755023e9201f21ff2","size":2188,"noattachment":false,"tarball":"https://registry.npm.taobao.org/domelementtype/download/domelementtype-2.0.0.tgz"},"maintainers":[{"name":"feedic","email":"me@feedic.com"}],"_npmUser":{"name":"feedic","email":"me@feedic.com"},"directories":{},"_npmOperationalInternal":{"host":"s3://npm-registry-packages","tmp":"tmp/domelementtype_2.0.0_1564511524080_0.6257425819943703"},"_hasShrinkwrap":false,"publish_time":1564511524234,"_cnpm_publish_time":1564511524234},"1.3.1":{"name":"domelementtype","version":"1.3.1","description":"all the types of nodes in htmlparser2's dom","main":"index.js","repository":{"type":"git","url":"git://github.com/fb55/domelementtype.git"},"keywords":["dom","htmlparser2"],"author":{"name":"Felix Boehm","email":"me@feedic.com"},"license":"BSD-2-Clause","gitHead":"19b2491101a4de3679b59db8eb7fdd9aa0fbc60b","bugs":{"url":"https://github.com/fb55/domelementtype/issues"},"homepage":"https://github.com/fb55/domelementtype#readme","_id":"domelementtype@1.3.1","_npmVersion":"6.4.1","_nodeVersion":"11.3.0","_npmUser":{"name":"feedic","email":"me@feedic.com"},"dist":{"shasum":"d048c44b37b0d10a7f2a3d5fee3f4333d790481f","size":1287,"noattachment":false,"tarball":"https://registry.npm.taobao.org/domelementtype/download/domelementtype-1.3.1.tgz"},"maintainers":[{"name":"feedic","email":"me@feedic.com"}],"directories":{},"_npmOperationalInternal":{"host":"s3://npm-registry-packages","tmp":"tmp/domelementtype_1.3.1_1544088453224_0.16246904901637227"},"_hasShrinkwrap":false,"publish_time":1544088453391,"_cnpm_publish_time":1544088453391},"1.2.1":{"name":"domelementtype","version":"1.2.1","description":"all the types of nodes in htmlparser2's dom","main":"index.js","repository":{"type":"git","url":"git://github.com/fb55/domelementtype.git"},"keywords":["dom","htmlparser2"],"author":{"name":"Felix Boehm","email":"me@feedic.com"},"license":"BSD-2-Clause","gitHead":"e34c657d2257df46ddf568cfee7cc83b7ae7eee2","bugs":{"url":"https://github.com/fb55/domelementtype/issues"},"homepage":"https://github.com/fb55/domelementtype#readme","_id":"domelementtype@1.2.1","_npmVersion":"6.4.1","_nodeVersion":"10.11.0","_npmUser":{"name":"feedic","email":"me@feedic.com"},"dist":{"shasum":"578558ef23befac043a1abb0db07635509393479","size":1287,"noattachment":false,"tarball":"https://registry.npm.taobao.org/domelementtype/download/domelementtype-1.2.1.tgz"},"maintainers":[{"name":"feedic","email":"me@feedic.com"}],"directories":{},"_npmOperationalInternal":{"host":"s3://npm-registry-packages","tmp":"tmp/domelementtype_1.2.1_1540165243735_0.9041202397017374"},"_hasShrinkwrap":false,"publish_time":1540165243885,"_cnpm_publish_time":1540165243885},"1.3.0":{"name":"domelementtype","version":"1.3.0","description":"all the types of nodes in htmlparser2's dom","main":"index.js","repository":{"type":"git","url":"git://github.com/FB55/domelementtype.git"},"keywords":["dom","htmlparser2"],"author":{"name":"Felix Boehm","email":"me@feedic.com"},"gitHead":"2a95eed4c829ef479a88984d117cb5f4b379e6e8","bugs":{"url":"https://github.com/FB55/domelementtype/issues"},"homepage":"https://github.com/FB55/domelementtype","_id":"domelementtype@1.3.0","scripts":{},"_shasum":"b17aed82e8ab59e52dd9c19b1756e0fc187204c2","_from":".","_npmVersion":"2.6.1","_nodeVersion":"1.4.2","_npmUser":{"name":"feedic","email":"me@feedic.com"},"maintainers":[{"name":"feedic","email":"me@feedic.com"}],"dist":{"shasum":"b17aed82e8ab59e52dd9c19b1756e0fc187204c2","size":1290,"noattachment":false,"tarball":"https://registry.npm.taobao.org/domelementtype/download/domelementtype-1.3.0.tgz"},"directories":{},"publish_time":1425376763974,"_cnpm_publish_time":1425376763974,"_hasShrinkwrap":false,"deprecated":"update to domelementtype@1.3.1"},"1.2.0":{"name":"domelementtype","version":"1.2.0","description":"all the types of nodes in htmlparser2's dom","main":"index.js","repository":{"type":"git","url":"git://github.com/FB55/domelementtype.git"},"keywords":["dom","htmlparser2"],"author":{"name":"Felix Boehm","email":"me@feedic.com"},"gitHead":"440f8830c8be5013de62363461f1149c7b419e72","bugs":{"url":"https://github.com/FB55/domelementtype/issues"},"homepage":"https://github.com/FB55/domelementtype","_id":"domelementtype@1.2.0","scripts":{},"_shasum":"03d93b0a0ea6ed3fb19f8dcc6ab9fb614720eb6c","_from":".","_npmVersion":"2.6.1","_nodeVersion":"1.4.2","_npmUser":{"name":"feedic","email":"me@feedic.com"},"maintainers":[{"name":"feedic","email":"me@feedic.com"}],"dist":{"shasum":"03d93b0a0ea6ed3fb19f8dcc6ab9fb614720eb6c","size":1291,"noattachment":false,"tarball":"https://registry.npm.taobao.org/domelementtype/download/domelementtype-1.2.0.tgz"},"directories":{},"publish_time":1425376631527,"_cnpm_publish_time":1425376631527,"_hasShrinkwrap":false},"1.1.3":{"name":"domelementtype","version":"1.1.3","description":"all the types of nodes in htmlparser2's dom","main":"index.js","repository":{"type":"git","url":"git://github.com/FB55/domelementtype.git"},"keywords":["dom","htmlparser2"],"author":{"name":"Felix Boehm","email":"me@feedic.com"},"gitHead":"012a97a1d38737e096de2045b2b5f28768d8187e","bugs":{"url":"https://github.com/FB55/domelementtype/issues"},"homepage":"https://github.com/FB55/domelementtype","_id":"domelementtype@1.1.3","scripts":{},"_shasum":"bd28773e2642881aec51544924299c5cd822185b","_from":".","_npmVersion":"2.1.5","_nodeVersion":"0.10.32","_npmUser":{"name":"feedic","email":"me@feedic.com"},"maintainers":[{"name":"feedic","email":"me@feedic.com"}],"dist":{"shasum":"bd28773e2642881aec51544924299c5cd822185b","size":1276,"noattachment":false,"tarball":"https://registry.npm.taobao.org/domelementtype/download/domelementtype-1.1.3.tgz"},"directories":{},"publish_time":1414667052175,"_cnpm_publish_time":1414667052175,"_hasShrinkwrap":false},"1.1.2":{"name":"domelementtype","version":"1.1.2","description":"all the types of nodes in htmlparser2's dom","main":"index.js","repository":{"type":"git","url":"git://github.com/FB55/domelementtype.git"},"keywords":["dom","htmlparser2"],"author":{"name":"Felix Boehm","email":"me@feedic.com"},"gitHead":"062ff89a17121c0a4f67ecb534f1677fbb50501a","bugs":{"url":"https://github.com/FB55/domelementtype/issues"},"homepage":"https://github.com/FB55/domelementtype","_id":"domelementtype@1.1.2","scripts":{},"_shasum":"795897af1f24cf2f4d287770698210bb0e826b7a","_from":".","_npmVersion":"2.1.5","_nodeVersion":"0.10.32","_npmUser":{"name":"feedic","email":"me@feedic.com"},"maintainers":[{"name":"feedic","email":"me@feedic.com"}],"dist":{"shasum":"795897af1f24cf2f4d287770698210bb0e826b7a","size":1276,"noattachment":false,"tarball":"https://registry.npm.taobao.org/domelementtype/download/domelementtype-1.1.2.tgz"},"directories":{},"publish_time":1414666916102,"_cnpm_publish_time":1414666916102,"_hasShrinkwrap":false},"1.1.1":{"name":"domelementtype","version":"1.1.1","description":"all the types of nodes in htmlparser2's dom","main":"index.js","repository":{"type":"git","url":"git://github.com/FB55/domelementtype.git"},"keywords":["dom","htmlparser2"],"author":{"name":"Felix Boehm","email":"me@feedic.com"},"readmeFilename":"readme.md","_id":"domelementtype@1.1.1","dist":{"shasum":"7887acbda7614bb0a3dbe1b5e394f77a8ed297cf","size":1294,"noattachment":false,"tarball":"https://registry.npm.taobao.org/domelementtype/download/domelementtype-1.1.1.tgz"},"_from":".","_npmVersion":"1.2.10","_npmUser":{"name":"feedic","email":"me@feedic.com"},"maintainers":[{"name":"feedic","email":"me@feedic.com"}],"directories":{},"publish_time":1360914193702,"_hasShrinkwrap":false,"_cnpm_publish_time":1360914193702},"1.1.0":{"name":"domelementtype","version":"1.1.0","description":"all the types of nodes in htmlparser2's dom","main":"index.js","repository":{"type":"git","url":"git://github.com/FB55/domelementtype.git"},"keywords":["dom","htmlparser2"],"author":{"name":"Felix Boehm","email":"me@feedic.com"},"readmeFilename":"readme.md","_id":"domelementtype@1.1.0","dist":{"shasum":"e200c6b5a2f67cf5296559647bf726d63714f5be","size":597,"noattachment":false,"tarball":"https://registry.npm.taobao.org/domelementtype/download/domelementtype-1.1.0.tgz"},"_npmVersion":"1.1.69","_npmUser":{"name":"feedic","email":"me@feedic.com"},"maintainers":[{"name":"feedic","email":"me@feedic.com"}],"directories":{},"publish_time":1357742889118,"_hasShrinkwrap":false,"_cnpm_publish_time":1357742889118},"1.0.1":{"name":"domelementtype","version":"1.0.1","description":"all the types of nodes in htmlparser2's dom","main":"index.js","repository":{"type":"git","url":"git://github.com/FB55/domelementtype.git"},"keywords":["dom","htmlparser2"],"author":{"name":"Felix Boehm","email":"me@feedic.com"},"_id":"domelementtype@1.0.1","dist":{"shasum":"70150a1bc6336298b0d6c4cbac27dcb66e06d86f","size":580,"noattachment":false,"tarball":"https://registry.npm.taobao.org/domelementtype/download/domelementtype-1.0.1.tgz"},"_npmVersion":"1.1.63","_npmUser":{"name":"feedic","email":"me@feedic.com"},"maintainers":[{"name":"feedic","email":"me@feedic.com"}],"directories":{},"publish_time":1354630550441,"_hasShrinkwrap":false,"_cnpm_publish_time":1354630550441},"1.0.0":{"name":"domelementtype","version":"1.0.0","description":"all the types of nodes in htmlparser2's dom","main":"index.js","repository":{"type":"git","url":"git://github.com/FB55/domelementtype.git"},"keywords":["dom","htmlparser2"],"author":{"name":"Felix Boehm","email":"me@feedic.com"},"readmeFilename":"readme.md","_id":"domelementtype@1.0.0","dist":{"shasum":"bdfe35bfeacb8ee61b19abaf473883f6b7227aca","size":548,"noattachment":false,"tarball":"https://registry.npm.taobao.org/domelementtype/download/domelementtype-1.0.0.tgz"},"_npmVersion":"1.1.65","_npmUser":{"name":"feedic","email":"me@feedic.com"},"maintainers":[{"name":"feedic","email":"me@feedic.com"}],"directories":{},"publish_time":1352554496751,"_hasShrinkwrap":false,"_cnpm_publish_time":1352554496751}},"readme":"All the types of nodes in htmlparser2's DOM.\n","_attachments":{},"homepage":"https://github.com/fb55/domelementtype#readme","bugs":{"url":"https://github.com/fb55/domelementtype/issues"},"license":"BSD-2-Clause","_etag":"W/\"f3f3ca2eebd88e3dca7ca150d2f83fe5\""}